{
	"auth": {
		"cydrasilwebapp9dbd2325": {
			"service": "Cognito",
			"providerPlugin": "awscloudformation",
			"dependsOn": [],
			"customAuth": false
		}
	},
	"storage": {
		"cydrasilPlaceFiles": {
			"service": "S3",
			"providerPlugin": "awscloudformation"
		}
	},
	"function": {
		"cydrasilPlacementWorkflowPY": {
			"service": "Lambda",
			"providerPlugin": "awscloudformation",
			"build": true,
			"dependsOn": [
				{
					"category": "auth",
					"resourceName": "cydrasilwebapp9dbd2325",
					"attributes": [
						"UserPoolId"
					]
				},
				{
					"category": "storage",
					"resourceName": "cydrasilPlaceFiles",
					"attributes": [
						"BucketName"
					]
				},
				{
					"category": "api",
					"resourceName": "CydrasilWebAppPlacementInfoDB",
					"attributes": [
						"GraphQLAPIIdOutput",
						"GraphQLAPIEndpointOutput"
					]
				}
			]
		}
	},
	"api": {
		"CydrasilWebAppPlacementInfoDB": {
			"service": "AppSync",
			"providerPlugin": "awscloudformation",
			"output": {
				"authConfig": {
					"additionalAuthenticationProviders": [],
					"defaultAuthentication": {
						"authenticationType": "AMAZON_COGNITO_USER_POOLS",
						"userPoolConfig": {
							"userPoolId": "authcydrasilwebapp9dbd2325"
						}
					}
				}
			}
		}
	},
	"hosting": {
		"S3AndCloudFront": {
			"service": "S3AndCloudFront",
			"providerPlugin": "awscloudformation"
		}
	}
}